kegstand/__init__.py
kegstand/api.py
kegstand/decorators.py
kegstand/utils.py
kegstand-0.4.0.dist-info/LICENSE
kegstand-0.4.0.dist-info/METADATA
kegstand-0.4.0.dist-info/WHEEL
kegstand-0.4.0.dist-info/RECORD
