Metadata-Version: 2.1
Name: kegstand
Version: 0.4.0
Summary: The Developer's Toolbelt For Accelerating Mean-Time-To-Party on AWS
Home-page: https://kegstand.dev
License: MIT
Author: JensRoland
Author-email: mail@jensroland.com
Requires-Python: >=3.10,<4.0
Classifier: Development Status :: 4 - Beta
Classifier: Intended Audience :: Developers
Classifier: License :: OSI Approved :: MIT License
Classifier: Operating System :: OS Independent
Classifier: Programming Language :: Python :: 3
Classifier: Programming Language :: Python :: 3.10
Classifier: Programming Language :: Python :: 3.11
Classifier: Programming Language :: Python :: 3.12
Classifier: Programming Language :: Python :: 3.13
Classifier: Topic :: Software Development :: Libraries :: Python Modules
Requires-Dist: aws-lambda-powertools[aws-sdk] (>=2.10.0,<3.0.0)
Requires-Dist: pyjwt (>=2.1.0,<3.0.0)
Project-URL: Repository, https://github.com/jensroland/kegstand-framework-python
